_build_cyrk.py
CyRK/__init__.pxd
CyRK/__init__.py
CyRK/_test.py
CyRK/helper.py
CyRK/array/__init__.pxd
CyRK/array/__init__.py
CyRK/array/__init__.pyx
CyRK/array/interp.cp313-win_amd64.pyd
CyRK/array/interp.pxd
CyRK/array/interp.pyx
CyRK/array/interp_common.c
CyRK/cy/__init__.pxd
CyRK/cy/__init__.py
CyRK/cy/c_common.cpp
CyRK/cy/c_common.hpp
CyRK/cy/c_events.cpp
CyRK/cy/c_events.hpp
CyRK/cy/common.cp313-win_amd64.pyd
CyRK/cy/common.pxd
CyRK/cy/common.pyx
CyRK/cy/cy_array.cpp
CyRK/cy/cy_array.hpp
CyRK/cy/cysolution.cpp
CyRK/cy/cysolution.hpp
CyRK/cy/cysolve.cpp
CyRK/cy/cysolve.hpp
CyRK/cy/cysolver.cpp
CyRK/cy/cysolver.hpp
CyRK/cy/cysolver_api.cp313-win_amd64.pyd
CyRK/cy/cysolver_api.pxd
CyRK/cy/cysolver_api.pyx
CyRK/cy/cysolver_test.cp313-win_amd64.pyd
CyRK/cy/cysolver_test.pxd
CyRK/cy/cysolver_test.pyx
CyRK/cy/dense.cpp
CyRK/cy/dense.hpp
CyRK/cy/events.cp313-win_amd64.pyd
CyRK/cy/events.pxd
CyRK/cy/events.pyx
CyRK/cy/events_test.cp313-win_amd64.pyd
CyRK/cy/events_test.pyx
CyRK/cy/helpers.cp313-win_amd64.pyd
CyRK/cy/helpers.pxd
CyRK/cy/helpers.pyx
CyRK/cy/pysolver.cp313-win_amd64.pyd
CyRK/cy/pysolver.pxd
CyRK/cy/pysolver.pyx
CyRK/cy/pysolver_cyhook.cp313-win_amd64.pyd
CyRK/cy/pysolver_cyhook.h
CyRK/cy/pysolver_cyhook.pxd
CyRK/cy/pysolver_cyhook.pyx
CyRK/cy/pysolver_cyhook_api.h
CyRK/cy/rk.cpp
CyRK/cy/rk.hpp
CyRK/nb/__init__.py
CyRK/nb/dop_coefficients.py
CyRK/nb/nb_storage.py
CyRK/nb/nbrk.py
CyRK/optimize/__init__.pxd
CyRK/optimize/__init__.py
CyRK/optimize/brentq.cp313-win_amd64.pyd
CyRK/optimize/brentq.pxd
CyRK/optimize/brentq.pyx
CyRK/optimize/c_brentq.cpp
CyRK/optimize/c_brentq.hpp
CyRK/optimize/optimize_test.cp313-win_amd64.pyd
CyRK/optimize/optimize_test.pyx
CyRK/utils/memory.cp313-win_amd64.pyd
CyRK/utils/memory.pxd
CyRK/utils/memory.pyx
CyRK/utils/parallel.pyx
CyRK/utils/utils.cp313-win_amd64.pyd
CyRK/utils/utils.pxd
CyRK/utils/utils.pyx
CyRK/utils/vector.cp313-win_amd64.pyd
CyRK/utils/vector.pxd
CyRK/utils/vector.pyx
Tests/A_Package_Tests/test_package.py
cyrk-0.16.1.dist-info/licenses/LICENSE.md
cyrk-0.16.1.dist-info/METADATA
cyrk-0.16.1.dist-info/WHEEL
cyrk-0.16.1.dist-info/top_level.txt
cyrk-0.16.1.dist-info/RECORD
