Metadata-Version: 2.4
Name: CyRK
Version: 0.16.1
Summary: Runge-Kutta ODE Integrator Implemented in Cython and Numba.
Author-email: "Joe P. Renaud" <joe.p.renaud@gmail.com>
License-Expression: CC-BY-NC-SA-4.0
Project-URL: Homepage, https://github.com/jrenaud90/CyRK
Project-URL: Bug Tracker, https://github.com/jrenaud90/CyRK/issues
Project-URL: Documentation, https://cyrk.readthedocs.io/en/latest/
Keywords: Scientific Computing,Runge-Kutta,Numerical Integration,ODEs,Ordinary Differential Equations,cython,numba,Integration
Classifier: Development Status :: 4 - Beta
Classifier: Operating System :: Microsoft :: Windows
Classifier: Operating System :: MacOS
Classifier: Operating System :: POSIX :: Linux
Classifier: Programming Language :: Cython
Classifier: Programming Language :: Python :: 3.9
Classifier: Programming Language :: Python :: 3.10
Classifier: Programming Language :: Python :: 3.11
Classifier: Programming Language :: Python :: 3.12
Classifier: Programming Language :: Python :: 3.13
Classifier: Programming Language :: Python :: Implementation :: CPython
Classifier: Natural Language :: English
Classifier: Intended Audience :: Science/Research
Classifier: Intended Audience :: Education
Classifier: Topic :: Scientific/Engineering
Classifier: Topic :: Scientific/Engineering :: Mathematics
Classifier: Topic :: Scientific/Engineering :: Physics
Requires-Python: <3.14,>=3.9
License-File: LICENSE.md
Requires-Dist: numba>=0.54.1
Requires-Dist: numpy<2.4,>=1.22
Requires-Dist: scipy>=1.9.3
Provides-Extra: dev
Requires-Dist: jupyter; extra == "dev"
Requires-Dist: matplotlib; extra == "dev"
Requires-Dist: pytest; extra == "dev"
Requires-Dist: timeit; extra == "dev"
Requires-Dist: line_profiler==3.5.1; extra == "dev"
Dynamic: license-file
